socra/__init__.py
socra/actions/__init__.py
socra/actions/base.py
socra/actions/files/modify_file.py
socra/actions/files/should_update.py
socra/actions/folders/__init__.py
socra/actions/folders/choose_mutation.py
socra/actions/llm/__init__.py
socra/agents/__init__.py
socra/agents/agent_decision.py
socra/agents/await_input/action.py
socra/agents/await_input/agent.yml
socra/agents/base.py
socra/agents/context.py
socra/agents/file_system/actions.py
socra/agents/file_system/agent.py
socra/agents/user_interaction/actions.py
socra/agents/user_interaction/agent.py
socra/cli.py
socra/commands/__init__.py
socra/commands/command.py
socra/commands/describe.py
socra/completions/__init__.py
socra/completions/base.py
socra/completions/usage.py
socra/constants.py
socra/files/__init__.py
socra/files/file.py
socra/files/folder.py
socra/io/__init__.py
socra/io/files.py
socra/messages/__init__.py
socra/messages/base.py
socra/models/__init__.py
socra/models/base.py
socra/nodes/__init__.py
socra/nodes/actions/__init__.py
socra/nodes/actions/add_child.py
socra/nodes/actions/content_update.py
socra/nodes/actions/root.py
socra/nodes/node.py
socra/parsers/__init__.py
socra/prompts/__init__.py
socra/prompts/base.py
socra/sandbox/CoolComponent.tsx
socra/sandbox/example.py
socra/sandbox/random.py
socra/schemas/__init__.py
socra/schemas/base.py
socra/utils/decorators.py
socra/utils/spinner.py
socra-0.0.9.dist-info/LICENSE
socra-0.0.9.dist-info/METADATA
socra-0.0.9.dist-info/WHEEL
socra-0.0.9.dist-info/entry_points.txt
socra-0.0.9.dist-info/RECORD
