Metadata-Version: 2.1
Name: socra
Version: 0.0.9
Summary: The official Python library of socra AI
License: MIT
Requires-Python: >=3.9,<4.0
Classifier: License :: OSI Approved :: MIT License
Classifier: Programming Language :: Python :: 3
Classifier: Programming Language :: Python :: 3.9
Classifier: Programming Language :: Python :: 3.10
Classifier: Programming Language :: Python :: 3.11
Classifier: Programming Language :: Python :: 3.12
Requires-Dist: click (>=8,<9)
Requires-Dist: inquirer (>=3.4.0,<4.0.0)
Requires-Dist: langchain (>=0.2,<0.3)
Requires-Dist: langchain-anthropic (>=0.1,<0.2)
Requires-Dist: langchain-community (>=0.2,<0.3)
Requires-Dist: langchain-openai (>=0.1,<0.2)
Requires-Dist: openai (>=1,<2)
Requires-Dist: pydantic (>=2,<3)
Requires-Dist: tiktoken (>=0.7,<0.8)
